markovgram/__init__.py
markovgram/__main__.py
markovgram/merge.py
markovgram/preview.py
markovgram-0.3.5.dist-info/entry_points.txt
markovgram-0.3.5.dist-info/WHEEL
markovgram-0.3.5.dist-info/METADATA
markovgram-0.3.5.dist-info/RECORD
